{
  "gw": "\u0b95\u0bc8\u0ba9\u0bc7-\u0baa\u0bbf\u0b9a\u0bcb", 
  "gu": "\u0b95\u0baf\u0bc1\u0bae\u0bcd", 
  "gt": "\u0b95\u0b9f\u0bc7\u0bae\u0bc7\u0bb2\u0bbe", 
  "gs": "\u0ba4\u0bc6\u0ba9\u0bcd \u0b9c\u0bbe\u0bb0\u0bcd\u0b9c\u0bbf\u0baf\u0bbe \u0bae\u0bb1\u0bcd\u0bb1\u0bc1\u0bae\u0bcd \u0ba4\u0bc6\u0ba9\u0bcd \u0b9a\u0bbe\u0ba9\u0bcd\u0bb5\u0bbf\u0b9f\u0bcd\u0b9c\u0bcd \u0ba4\u0bc0\u0bb5\u0bc1\u0b95\u0bb3\u0bcd", 
  "gr": "\u0b95\u0bcd\u0bb0\u0bc0\u0bb8\u0bcd", 
  "gq": "\u0bae\u0ba4\u0bcd\u0ba4\u0bbf\u0baf \u0b95\u0bcd\u0ba9\u0bbf\u0baf\u0bbe", 
  "gp": "\u0b95\u0bcb\u0b9f\u0bbf\u0bb2\u0bcb\u0baa\u0bcd", 
  "gy": "\u0b95\u0bcd\u0baf\u0bbe\u0ba9\u0bbe", 
  "gg": "\u0b95\u0bc1\u0bb0\u0bcd\u0ba9\u0bcd\u0b9a\u0bc7", 
  "gf": "\u0baa\u0bbf\u0bb0\u0b9e\u0bcd\u0b9a\u0bc1 \u0b95\u0bc1\u0baf\u0bcd\u0ba9\u0bbe", 
  "ge": "\u0b9c\u0bbe\u0bb0\u0bcd\u0b9c\u0bbf\u0baf\u0bbe", 
  "gd": "\u0b95\u0bbf\u0bb0\u0bc0\u0ba8\u0bbe\u0b9f\u0bbe", 
  "gb": "\u0b90\u0b95\u0bcd\u0b95\u0bbf\u0baf \u0b85\u0bb0\u0b9a\u0bc1", 
  "ga": "\u0b95\u0bbe\u0baa\u0bcb\u0ba9\u0bcd", 
  "gn": "\u0b95\u0bcd\u0ba9\u0bbf\u0baf\u0bbe", 
  "gm": "\u0b95\u0bbe\u0bae\u0bcd\u0baa\u0bbf\u0baf\u0bbe", 
  "gl": "\u0b95\u0bcd\u0bb0\u0bc0\u0ba9\u0bcd\u0bb2\u0bbe\u0ba8\u0bcd\u0ba4\u0bc1", 
  "gi": "\u0b95\u0bbf\u0baa\u0bcd\u0bb0\u0bbe\u0bb2\u0bcd\u0b9f\u0bb0\u0bcd", 
  "gh": "\u0b95\u0bbe\u0ba9\u0bbe", 
  "tz": "\u0ba4\u0bbe\u0ba9\u0bcd\u0b9a\u0bbe\u0ba9\u0bbf\u0baf\u0bbe", 
  "lc": "\u0b9a\u0bc6\u0baf\u0bbf\u0ba3\u0bcd\u0b9f\u0bcd \u0bb2\u0bc2\u0b9a\u0bbf\u0baf\u0bbe", 
  "la": "\u0bb2\u0bcb\u0bb8\u0bcd", 
  "tv": "\u0ba4\u0bc1\u0bb5\u0bbe\u0bb2\u0bc1", 
  "tw": "\u0ba4\u0bbe\u0baf\u0bcd\u0bb5\u0bbe\u0ba9\u0bcd", 
  "tt": "\u0b9f\u0bcd\u0bb0\u0bc0\u0ba9\u0bbf\u0ba4\u0ba4\u0bcd \u0bae\u0bb1\u0bcd\u0bb1\u0bc1\u0bae\u0bcd \u0b9f\u0bcb\u0baa\u0bbe\u0b95\u0bcb", 
  "tr": "\u0b9f\u0bb0\u0bcd\u0b95\u0bbf", 
  "lk": "\u0b87\u0bb2\u0b99\u0bcd\u0b95\u0bc8", 
  "li": "\u0bb2\u0bc8\u0b9a\u0bbf\u0b9f\u0bc6\u0ba9\u0bcd\u0bb8\u0bcd\u0b9f\u0bc0\u0ba9\u0bcd", 
  "tn": "\u0ba4\u0bc1\u0ba9\u0bc0\u0bb8\u0bbf\u0baf\u0bbe", 
  "to": "\u0b9f\u0bcb\u0ba9\u0bcd\u0b95\u0bbe", 
  "tl": "\u0ba4\u0bc8\u0bae\u0bc2\u0bb0\u0bcd-\u0bb2\u0bb8\u0bcd\u0b9f\u0bc7", 
  "tm": "\u0ba4\u0bc1\u0bb0\u0bc1\u0b95\u0bcd\u0bae\u0bc7\u0ba9\u0bbf\u0bb8\u0bcd\u0ba4\u0bbe\u0ba9\u0bcd", 
  "tj": "\u0ba4\u0b9c\u0bbf\u0b95\u0bbf\u0bb8\u0bcd\u0ba4\u0bbe\u0ba9\u0bcd", 
  "tk": "\u0b9f\u0bcb\u0b95\u0bbf\u0bb2\u0bcb", 
  "th": "\u0ba4\u0bbe\u0baf\u0bcd\u0bb2\u0bbe\u0ba8\u0bcd\u0ba4\u0bc1", 
  "tf": "\u0baa\u0bbf\u0bb0\u0bc6\u0b9e\u0bcd\u0b9a\u0bc1 \u0ba4\u0bc6\u0ba9\u0bcd \u0baa\u0bbf\u0bb0\u0ba4\u0bc7\u0b9a\u0b99\u0bcd\u0b95\u0bb3\u0bcd", 
  "tg": "\u0b9f\u0bcb\u0b95\u0bcb", 
  "td": "\u0b9a\u0bbe\u0b9f\u0bcd", 
  "tc": "\u0b9f\u0bcd\u0bb0\u0b95\u0bcd\u0bb8\u0bcd \u0bae\u0bb1\u0bcd\u0bb1\u0bc1\u0bae\u0bcd \u0b95\u0bbe\u0baf\u0bcd\u0b95\u0bcb\u0bb8\u0bcd \u0ba4\u0bc0\u0bb5\u0bc1\u0b95\u0bb3\u0bcd", 
  "ly": "\u0bb2\u0bbf\u0baa\u0bbf\u0baf\u0bbe", 
  "do": "\u0b9f\u0bcb\u0bae\u0bcd\u0ba9\u0bbf\u0b95\u0bbe\u0ba9\u0bcd \u0b95\u0bc1\u0b9f\u0bbf\u0baf\u0bb0\u0b9a\u0bc1", 
  "dm": "\u0b9f\u0bcb\u0bae\u0bcd\u0ba9\u0bbf\u0b95\u0bbe", 
  "dj": "\u0b9f\u0bbf\u0b9c\u0bbf\u0baa\u0bcb\u0b9f\u0bbf", 
  "dk": "\u0b9f\u0bc6\u0ba9\u0bcd\u0bae\u0bbe\u0bb0\u0bcd\u0b95\u0bcd", 
  "de": "\u0b9c\u0bc6\u0bb0\u0bcd\u0bae\u0ba9\u0bbf", 
  "ye": "\u0b8f\u0bae\u0ba9\u0bcd", 
  "dz": "\u0b85\u0bb2\u0bcd\u0b95\u0bc7\u0bb0\u0bbf\u0baf\u0bbe", 
  "ma": "\u0bae\u0bcb\u0bb0\u0bcb\u0b95\u0bcb", 
  "yt": "\u0bae\u0baf\u0bcb\u0b9f\u0bc0", 
  "vu": "\u0bb5\u0bc7\u0ba9\u0bcb\u0b9f\u0bcd\u0b9f\u0bc1", 
  "qa": "\u0b95\u0ba4\u0bcd\u0ba4\u0bbe\u0bb0\u0bcd", 
  "lv": "\u0bb2\u0b9f\u0bcd\u0bb5\u0bbf\u0baf\u0bbe", 
  "zm": "\u0bb8\u0bbe\u0bae\u0bcd\u0baa\u0bbf\u0baf\u0bbe", 
  "eh": "\u0bae\u0bc7\u0bb1\u0bcd\u0b95\u0bc1 \u0b9a\u0b95\u0bbe\u0bb0\u0bbe", 
  "wf": "\u0bb5\u0bbe\u0bb2\u0bbf\u0bb8\u0bcd \u0bae\u0bb1\u0bcd\u0bb1\u0bc1\u0bae\u0bcd \u0b83\u0baa\u0bc2\u0b9f\u0bcd\u0b9f\u0bc1\u0ba9\u0bbe", 
  "ee": "\u0b87\u0bb8\u0bcd\u0b9f\u0bcb\u0ba9\u0bbf\u0baf\u0bbe", 
  "eg": "\u0b8e\u0b95\u0bbf\u0baa\u0bcd\u0ba4\u0bc1", 
  "za": "\u0ba4\u0bc6\u0bb1\u0bcd\u0b95\u0bc1 \u0b86\u0b83\u0baa\u0bcd\u0bb0\u0bbf\u0b95\u0bbe", 
  "ec": "\u0b88\u0b95\u0bc1\u0bb5\u0bc7\u0b9f\u0bbe\u0bb0\u0bcd", 
  "mk": "\u0bae\u0bc6\u0b9a\u0bbf\u0b9f\u0bcb\u0ba9\u0bbf\u0baf\u0bbe , F.Y.R.", 
  "et": "\u0b8e\u0ba4\u0bcd\u0ba4\u0bbf\u0baf\u0bcb\u0baa\u0bcd\u0baa\u0bbf\u0baf\u0bbe", 
  "zw": "\u0b9c\u0bbf\u0bae\u0bcd\u0baa\u0bbe\u0baa\u0bcd\u0bb5\u0bc7", 
  "lb": "\u0bb2\u0bc6\u0baa\u0ba9\u0bbe\u0ba9\u0bcd", 
  "er": "\u0b8e\u0bb0\u0bbf\u0ba4\u0bcd\u0ba4\u0bbf\u0bb0\u0bbf\u0baf\u0bbe", 
  "mu": "\u0bae\u0bca\u0bb0\u0bc0\u0bb7\u0bbf\u0baf\u0bb8\u0bcd", 
  "rw": "\u0bb0\u0bc1\u0bb5\u0bbe\u0ba3\u0bcd\u0b9f\u0bbe", 
  "bh": "\u0baa\u0bc6\u0bb9\u0bb0\u0bc8\u0ba9\u0bcd", 
  "rs": "\u0b9a\u0bc6\u0bb0\u0bcd\u0baa\u0bbf\u0baf\u0bbe", 
  "re": "\u0bb0\u0bc0\u0baf\u0bc1\u0ba9\u0bbf\u0baf\u0ba9\u0bcd", 
  "ro": "\u0bb0\u0bcb\u0bae\u0bbe\u0ba9\u0bbf\u0baf\u0bbe", 
  "bd": "\u0bb5\u0b99\u0bcd\u0b95\u0bbe\u0bb3\u0ba4\u0bc7\u0b9a\u0bae\u0bcd", 
  "be": "\u0baa\u0bc6\u0bb2\u0bcd\u0b9c\u0bbf\u0baf\u0bae\u0bcd", 
  "bf": "\u0baa\u0bb0\u0bcd\u0b95\u0bbf\u0ba9\u0bbe \u0b83\u0baa\u0bbe\u0b9a\u0bcb", 
  "bg": "\u0baa\u0bb2\u0bcd\u0b95\u0bc7\u0bb0\u0bbf\u0baf\u0bbe", 
  "vg": "\u0baa\u0bbf\u0bb0\u0bbf\u0b9f\u0bcd\u0b9f\u0bbf\u0bb7\u0bcd \u0bb5\u0bc6\u0bb0\u0bcd\u0b9c\u0bbf\u0ba9\u0bcd \u0ba4\u0bc0\u0bb5\u0bc1\u0b95\u0bb3\u0bcd", 
  "ba": "\u0baa\u0bcb\u0bb8\u0bcd\u0ba9\u0bbf\u0baf\u0bbe \u0bae\u0bb1\u0bcd\u0bb1\u0bc1\u0bae\u0bcd \u0bb9\u0bc7\u0bb0\u0bcd\u0b9a\u0bbf\u0b95\u0bcb\u0ba9\u0bbf\u0baf\u0bbe", 
  "bb": "\u0baa\u0bbe\u0bb0\u0bcd\u0baa\u0ba4\u0bbe\u0bb8\u0bcd", 
  "bl": "\u0b9a\u0bc6\u0baf\u0bbf\u0ba3\u0bcd\u0b9f\u0bcd \u0baa\u0bbe\u0bb0\u0bcd\u0ba4\u0bcd\u00e9lemy", 
  "bm": "\u0baa\u0bb0\u0bcd\u0bae\u0bc1\u0b9f\u0bbe", 
  "bn": "\u0baa\u0bcd\u0bb0\u0bc2\u0ba9\u0bc8 \u0ba4\u0bb0\u0bc1\u0b9a\u0bb2\u0bbe\u0bae\u0bcd", 
  "bo": "\u0baa\u0bca\u0bb2\u0bbf\u0bb5\u0bbf\u0baf\u0bbe", 
  "jp": "\u0b9c\u0baa\u0bcd\u0baa\u0bbe\u0ba9\u0bcd", 
  "bi": "\u0baa\u0bcd\u0bb0\u0bc2\u0ba3\u0bcd\u0ba4\u0bc0", 
  "bj": "\u0baa\u0bbf\u0ba9\u0bbf\u0ba9\u0bcd", 
  "bt": "\u0baa\u0bc2\u0b9f\u0bbe\u0ba9\u0bcd", 
  "jm": "\u0b9c\u0bae\u0bbe\u0baf\u0bcd\u0b95\u0bbe", 
  "bv": "\u0baa\u0bcb\u0bb5\u0b9f\u0bcd \u0ba4\u0bc0\u0bb5\u0bc1\u0b95\u0bb3\u0bcd", 
  "jo": "\u0b9c\u0bcb\u0bb0\u0bcd\u0ba4\u0bbe\u0ba9\u0bcd", 
  "ws": "\u0bb8\u0bbe\u0bae\u0bcb", 
  "no": "\u0ba8\u0bbe\u0bb0\u0bcd\u0bb5\u0bc7", 
  "br": "\u0baa\u0bbf\u0bb0\u0bc7\u0b9a\u0bbf\u0bb2\u0bcd", 
  "bs": "\u0baa\u0bb9\u0bbe\u0bae\u0bbe\u0bb8\u0bcd", 
  "je": "\u0b9c\u0bc6\u0bb0\u0bcd\u0b9a\u0bbf", 
  "by": "\u0baa\u0bc6\u0bb2\u0bbe\u0bb0\u0bb8\u0bcd", 
  "bz": "\u0baa\u0bbf\u0bb2\u0bc0\u0bb8\u0bcd", 
  "om": "\u0b93\u0bae\u0ba9\u0bcd", 
  "my": "\u0bae\u0bb2\u0bc7\u0bb7\u0bbf\u0baf\u0bbe", 
  "lr": "\u0bb2\u0bc8\u0baa\u0bc0\u0bb0\u0bbf\u0baf\u0bbe", 
  "bw": "\u0baa\u0bcb\u0b9f\u0bcd\u0bb8\u0bcd\u0bb5\u0bbe\u0ba9\u0bbe", 
  "mz": "\u0bae\u0bcb\u0bb8\u0bbe\u0bae\u0bcd\u0baa\u0bbf\u0b95\u0bcd", 
  "ck": "\u0b95\u0bc1\u0b95\u0bcd \u0ba4\u0bc0\u0bb5\u0bc1\u0b95\u0bb3\u0bcd", 
  "ci": "\u0b90\u0bb5\u0bc7\u0bb0\u0bbf \u0b95\u0b9f\u0bb1\u0bcd\u0b95\u0bb0\u0bc8", 
  "ch": "\u0b9a\u0bc1\u0bb5\u0b9f\u0bcd\u0b9a\u0bb0\u0bcd\u0bb2\u0bbe\u0ba8\u0bcd\u0ba4\u0bc1", 
  "co": "\u0b95\u0bca\u0bb2\u0bae\u0bcd\u0baa\u0bbf\u0baf\u0bbe", 
  "cn": "\u0b9a\u0bc0\u0ba9\u0bbe", 
  "cm": "\u0b95\u0bc7\u0bae\u0bcd\u0bb0\u0bc2\u0ba9\u0bcd", 
  "cl": "\u0b9a\u0bbf\u0bb2\u0bbf", 
  "cc": "\u0b95\u0bcb\u0b95\u0bcb\u0bb8\u0bcd (\u0b95\u0bc0\u0bb2\u0bbf\u0b99\u0bcd) \u0ba4\u0bc0\u0bb5\u0bc1\u0b95\u0bb3\u0bcd", 
  "ca": "\u0b95\u0ba9\u0b9f\u0bbe", 
  "cg": "\u0b95\u0bbe\u0b99\u0bcd\u0b95\u0bcb-\u0baa\u0bcd\u0bb0\u0bc7\u0b9a\u0bbe\u0bb5\u0bbf\u0bb2\u0bcd\u0bb2\u0bc7", 
  "cf": "\u0bae\u0ba4\u0bcd\u0ba4\u0bbf\u0baf \u0b86\u0baa\u0bcd\u0baa\u0bbf\u0bb0\u0bbf\u0b95\u0bcd\u0b95 \u0b95\u0bc1\u0b9f\u0bbf\u0baf\u0bb0\u0b9a\u0bc1", 
  "cd": "\u0b95\u0bbe\u0b99\u0bcd\u0b95\u0bcb-\u0b95\u0bbf\u0ba9\u0bcd\u0bb7\u0bbe\u0b9a\u0bbe", 
  "cz": "\u0b9a\u0bc6\u0b95\u0bcd \u0b95\u0bc1\u0b9f\u0bbf\u0baf\u0bb0\u0b9a\u0bc1", 
  "cy": "\u0b9a\u0bc8\u0baa\u0bcd\u0bb0\u0bb8\u0bcd", 
  "cx": "\u0b95\u0bbf\u0bb0\u0bbf\u0bb8\u0bcd\u0bae\u0bb8\u0bcd \u0ba4\u0bc0\u0bb5\u0bc1", 
  "cr": "\u0b95\u0bcb\u0bb8\u0bcd\u0b9f\u0bbe \u0bb0\u0bbf\u0b95\u0bbe", 
  "cv": "\u0b95\u0bc7\u0baa\u0bcd \u0bb5\u0bb0\u0bcd\u0b9f\u0bbf", 
  "cu": "\u0b95\u0bcd\u0baf\u0bc2\u0baa\u0bbe", 
  "ve": "\u0bb5\u0bc6\u0ba9\u0bbf\u0b9a\u0bc2\u0bb2\u0bbe", 
  "pr": "\u0baa\u0bcd\u0baf\u0bc1\u0bb0\u0bcd\u0b9f\u0bcb \u0bb0\u0bbf\u0b95\u0bcb", 
  "ps": "\u0b86\u0b95\u0bcd\u0b95\u0bbf\u0bb0\u0bae\u0bbf\u0b95\u0bcd\u0b95\u0baa\u0bcd\u0baa\u0b9f\u0bcd\u0b9f \u0baa\u0bbe\u0bb2\u0bb8\u0bcd\u0ba4\u0bc0\u0ba9 \u0baa\u0bbf\u0bb0\u0ba4\u0bc7\u0b9a\u0bae\u0bcd", 
  "pw": "\u0baa\u0bbe\u0bb2\u0bcb", 
  "pt": "\u0baa\u0bcb\u0bb0\u0bcd\u0b9a\u0bcd\u0b9a\u0bc1\u0b95\u0bb2\u0bcd", 
  "py": "\u0baa\u0bb0\u0bbe\u0b95\u0bc1\u0bb5\u0bc7", 
  "lt": "\u0bb2\u0bc2\u0ba4\u0bbf\u0baf\u0bbe\u0ba9\u0bbe", 
  "ls": "\u0bb2\u0bbf\u0bb8\u0bcb\u0ba4\u0bcb", 
  "fm": "\u0bae\u0bc8\u0b95\u0bcd\u0bb0\u0bcb\u0ba9\u0bc0\u0bb8\u0bbf\u0baf\u0bbe", 
  "iq": "\u0b88\u0bb0\u0bbe\u0b95\u0bcd", 
  "pa": "\u0baa\u0ba9\u0bbe\u0bae\u0bbe", 
  "pf": "\u0baa\u0bbf\u0bb0\u0b9e\u0bcd\u0b9a\u0bc1 \u0baa\u0bbe\u0bb2\u0bbf\u0ba9\u0bc7\u0bb7\u0bbf\u0baf\u0bbe", 
  "pg": "\u0baa\u0bbe\u0baa\u0bcd\u0baf\u0bbe \u0baa\u0bc1\u0ba4\u0bbf\u0baf \u0b95\u0bc1\u0ba9\u0bbf\u0baf\u0bbe", 
  "pe": "\u0baa\u0bc6\u0bb0\u0bc1", 
  "pk": "\u0baa\u0bbe\u0b95\u0bbf\u0bb8\u0bcd\u0ba4\u0bbe\u0ba9\u0bcd", 
  "ph": "\u0baa\u0bbf\u0bb2\u0bbf\u0baa\u0bc8\u0ba9\u0bcd\u0bb8\u0bcd", 
  "pn": "\u0baa\u0bbf\u0b9f\u0bcd\u0b95\u0bc8\u0bb0\u0ba9\u0bcd", 
  "pl": "\u0baa\u0bcb\u0bb2\u0ba8\u0bcd\u0ba4\u0bc1", 
  "pm": "\u0b9a\u0bc6\u0baf\u0bbf\u0ba3\u0bcd\u0b9f\u0bcd \u0baa\u0bc8\u0bb0\u0bc7 \u0bae\u0bb1\u0bcd\u0bb1\u0bc1\u0bae\u0bcd \u0bae\u0bbf\u0b95\u0bcd\u0baf\u0bc1\u0bb2\u0bbe\u0ba9\u0bcd", 
  "hu": "\u0bb9\u0b99\u0bcd\u0b95\u0bc7\u0bb0\u0bbf", 
  "hr": "\u0b95\u0bc1\u0bb0\u0bc7\u0bb7\u0bbf\u0baf\u0bbe", 
  "ht": "\u0bb9\u0baf\u0bcd\u0b9f\u0bbf", 
  "it": "\u0b87\u0ba4\u0bcd\u0ba4\u0bbe\u0bb2\u0bbf", 
  "hk": "\u0bb9\u0bbe\u0b99\u0bcd \u0b95\u0bbe\u0b99\u0bcd", 
  "lu": "\u0bb2\u0bc6\u0b95\u0bcd\u0bb8\u0bae\u0bcd\u0baa\u0bcb\u0bb0\u0bcd\u0b95\u0bcd", 
  "hn": "\u0bb9\u0bbe\u0ba9\u0bcd\u0b9f\u0bc1\u0bb0\u0bc2\u0bb8\u0bcd", 
  "vn": "\u0bb5\u0bbf\u0baf\u0b9f\u0bcd\u0ba8\u0bbe\u0bae\u0bcd", 
  "hm": "\u0bb9\u0bbf\u0baf\u0bb0\u0bcd\u0b9f\u0bc1 \u0ba4\u0bc0\u0bb5\u0bc1 \u0bae\u0bb1\u0bcd\u0bb1\u0bc1\u0bae\u0bcd \u0bae\u0bc6\u0b95\u0bcd\u0b9f\u0bcb\u0ba9\u0bbe\u0bb2\u0bcd\u0b9f\u0bc1 \u0ba4\u0bc0\u0bb5\u0bc1\u0b95\u0bb3\u0bcd", 
  "an": "\u0ba8\u0bc6\u0ba4\u0bb0\u0bcd\u0bb2\u0bbe\u0ba8\u0bcd\u0ba4\u0bc1 \u0b86\u0ba3\u0bcd\u0b9f\u0bbf\u0bb2\u0bcd\u0bb2\u0bb8\u0bcd", 
  "me": "\u0bae\u0bbe\u0ba3\u0bcd\u0b9f\u0bbf\u0ba8\u0b95\u0bb0\u0bcb", 
  "md": "\u0bae\u0bbe\u0bb2\u0bcd\u0b9f\u0bcb\u0bb5\u0bbe", 
  "mg": "\u0bae\u0b9f\u0b95\u0bbe\u0bb8\u0bcd\u0b95\u0bb0\u0bcd", 
  "mf": "\u0b9a\u0bc6\u0baf\u0bbf\u0ba9\u0bcd\u0b9f\u0bcd \u0bae\u0bbe\u0bb0\u0bcd\u0b9f\u0bbf\u0ba9\u0bcd", 
  "uy": "\u0b89\u0bb0\u0bc1\u0b95\u0bc1\u0bb5\u0bc7", 
  "mc": "\u0bae\u0bcb\u0ba9\u0bbe\u0b95\u0bcb", 
  "uz": "\u0b89\u0bb8\u0bcd\u0baa\u0bc6\u0b95\u0bbf\u0bb8\u0bcd\u0ba4\u0bbe\u0ba9\u0bcd", 
  "mm": "\u0bae\u0baf\u0ba9\u0bcd\u0bae\u0bbe\u0bb0\u0bcd", 
  "ml": "\u0bae\u0bbe\u0bb2\u0bbf", 
  "mo": "\u0bae\u0bbe\u0b95\u0bcb", 
  "mn": "\u0bae\u0b99\u0bcd\u0b95\u0bcb\u0bb2\u0bbf\u0baf\u0bbe", 
  "mh": "\u0bae\u0bbe\u0bb0\u0bcd\u0bb7\u0bb2\u0bcd \u0ba4\u0bc0\u0bb5\u0bc1\u0b95\u0bb3\u0bcd", 
  "us": "\u0b90\u0b95\u0bcd\u0b95\u0bbf\u0baf \u0b85\u0bae\u0bc6\u0bb0\u0bbf\u0b95\u0bcd\u0b95\u0bbe", 
  "um": "\u0b90\u0b95\u0bcd\u0b95\u0bbf\u0baf \u0b85\u0bae\u0bc6\u0bb0\u0bbf\u0b95\u0bcd\u0b95 \u0bae\u0bc8\u0ba9\u0bb0\u0bcd \u0b85\u0bb5\u0bc1\u0b9f\u0bcd\u0bb2\u0bc7\u0baf\u0bbf\u0b99\u0bcd \u0ba4\u0bc0\u0bb5\u0bc1\u0b95\u0bb3\u0bcd", 
  "mt": "\u0bae\u0bbe\u0bb2\u0bcd\u0b9f\u0bbe", 
  "mw": "\u0bae\u0bb2\u0bbe\u0bb5\u0bbf", 
  "mv": "\u0bae\u0bbe\u0bb2\u0bcd\u0ba4\u0bc0\u0bb5\u0bc1\u0b95\u0bb3\u0bcd", 
  "mq": "\u0bae\u0bbe\u0bb0\u0bcd\u0b9f\u0bbf\u0ba9\u0bbf\u0b95\u0bcd\u0baf\u0bc2", 
  "mp": "\u0bb5\u0b9f\u0b95\u0bcd\u0b95\u0bc1 \u0bae\u0bb0\u0bbf\u0baf\u0bbe\u0ba9 \u0ba4\u0bc0\u0bb5\u0bc1\u0b95\u0bb3\u0bcd", 
  "ms": "\u0bae\u0bbe\u0ba3\u0bcd\u0b9f\u0bcd\u0bb8\u0bcd\u0bb0\u0b9f\u0bcd", 
  "mr": "\u0bae\u0bcc\u0bb0\u0bbf\u0b9f\u0bbf\u0ba9\u0bbf\u0baf\u0bbe", 
  "im": "\u0bb8\u0bcd\u0bb2\u0bc7 \u0b86\u0baa\u0bcd \u0bae\u0bc7\u0ba9\u0bcd", 
  "ug": "\u0b89\u0b95\u0bbe\u0ba9\u0bcd\u0b9f\u0bbe", 
  "ua": "\u0b89\u0b95\u0bcd\u0bb0\u0bc6\u0baf\u0bcd\u0ba9\u0bbf", 
  "mx": "\u0bae\u0bc6\u0b95\u0bcd\u0bb8\u0bbf\u0b95\u0bcb", 
  "il": "\u0b87\u0bb8\u0bcd\u0bb0\u0bc7\u0bb2\u0bcd", 
  "va": "\u0bb5\u0bbe\u0b9f\u0bbf\u0b95\u0bbe\u0ba9\u0bcd \u0ba8\u0b95\u0bb0\u0bae\u0bcd", 
  "vc": "\u0b9a\u0bc6\u0baf\u0bbf\u0ba3\u0bcd\u0b9f\u0bcd \u0bb5\u0bbf\u0ba9\u0bcd\u0b9a\u0bc6\u0ba9\u0bcd\u0b9f\u0bcd \u0bae\u0bb1\u0bcd\u0bb1\u0bc1\u0bae\u0bcd \u0b95\u0bcd\u0bb0\u0bc0\u0ba9\u0b9f\u0bbf\u0ba9\u0bcd\u0bb8\u0bcd", 
  "ae": "U.A.E.", 
  "ad": "\u0b85\u0ba3\u0bcd\u0b9f\u0bcb\u0bb0\u0bbe", 
  "ag": "\u0b86\u0ba3\u0bcd\u0b9f\u0bbf\u0b95\u0bcd\u0bb5\u0bbe \u0bae\u0bb1\u0bcd\u0bb1\u0bc1\u0bae\u0bcd \u0baa\u0bbe\u0bb0\u0bcd\u0baa\u0bc1\u0b9f\u0bbe", 
  "af": "\u0b86\u0baa\u0bcd\u0b95\u0bbe\u0ba9\u0bbf\u0bb8\u0bcd\u0ba4\u0bbe\u0ba9\u0bcd", 
  "ai": "\u0b86\u0b99\u0bcd\u0b95\u0bc1\u0baf\u0bcd\u0bb2\u0bbe", 
  "vi": "U.S. \u0bb5\u0bc6\u0bb0\u0bcd\u0b9c\u0bbf\u0ba9\u0bcd \u0ba4\u0bc0\u0bb5\u0bc1\u0b95\u0bb3\u0bcd", 
  "is": "\u0b90\u0bb8\u0bcd\u0bb2\u0bbe\u0ba8\u0bcd\u0ba4\u0bc1", 
  "ir": "\u0b88\u0bb0\u0bbe\u0ba9\u0bcd", 
  "am": "\u0b86\u0bb0\u0bcd\u0bae\u0bc7\u0ba9\u0bbf\u0baf\u0bbe", 
  "al": "\u0b85\u0bb2\u0bcd\u0baa\u0bbe\u0ba9\u0bbf\u0baf\u0bbe", 
  "ao": "\u0b85\u0ba9\u0bcd\u0b95\u0bcb\u0bb2\u0bbe", 
  "kn": "\u0b9a\u0bc6\u0baf\u0bbf\u0ba9\u0bcd\u0b9f\u0bcd \u0b95\u0bbf\u0b9f\u0bbf\u0bb8\u0bcd \u0bae\u0bb1\u0bcd\u0bb1\u0bc1\u0bae\u0bcd \u0ba8\u0bc7\u0bb5\u0bbf\u0bb8\u0bcd", 
  "aq": "\u0b85\u0ba9\u0bcd\u0b9f\u0bbe\u0bb0\u0bcd\u0b9f\u0bbf\u0b95\u0bbe", 
  "as": "\u0b85\u0bae\u0bc6\u0bb0\u0bbf\u0b95\u0bcd\u0b95\u0ba9\u0bcd \u0b9a\u0bcb\u0bae\u0bcb", 
  "ar": "\u0b85\u0bb0\u0bcd\u0b9c\u0bc6\u0ba3\u0bcd\u0b9f\u0bbe", 
  "au": "\u0b86\u0bb8\u0bcd\u0ba4\u0bbf\u0bb0\u0bc7\u0bb2\u0bbf\u0baf\u0bbe", 
  "at": "\u0b86\u0bb8\u0bcd\u0b9f\u0bcd\u0bb0\u0bbf\u0baf\u0bbe", 
  "aw": "\u0b85\u0bb0\u0bc2\u0baa\u0bbe", 
  "in": "\u0b87\u0ba8\u0bcd\u0ba4\u0bbf\u0baf\u0bbe", 
  "ax": "\u00c5land \u0ba4\u0bc0\u0bb5\u0bc1\u0b95\u0bb3\u0bcd", 
  "az": "\u0b85\u0b9a\u0bb0\u0bcd\u0baa\u0bc8\u0b9c\u0bbe\u0ba9\u0bcd", 
  "ie": "\u0b85\u0baf\u0bb0\u0bcd\u0bb2\u0bbe\u0ba8\u0bcd\u0ba4\u0bc1", 
  "id": "\u0b87\u0ba8\u0bcd\u0ba4\u0bcb\u0ba9\u0bc7\u0bb7\u0bbf\u0baf\u0bbe", 
  "ni": "\u0ba8\u0bc8\u0b95\u0bb0\u0bbe\u0b95\u0bc1\u0baf\u0bbe", 
  "nl": "\u0ba8\u0bc6\u0ba4\u0bb0\u0bcd\u0bb2\u0bbe\u0ba8\u0bcd\u0ba4\u0bc1", 
  "kr": "\u0ba4\u0bc6\u0bb1\u0bcd\u0b95\u0bc1 \u0b95\u0bca\u0bb0\u0bbf\u0baf\u0bbe", 
  "na": "\u0ba8\u0bae\u0bc0\u0baa\u0bbf\u0baf\u0bbe", 
  "nc": "\u0ba8\u0bbf\u0baf\u0bc2 \u0b95\u0bb2\u0bbf\u0b9f\u0bcb\u0ba9\u0bbf\u0baf\u0bbe", 
  "ne": "\u0ba8\u0bc8\u0b95\u0bb0\u0bcd", 
  "nf": "\u0ba8\u0bbe\u0bb0\u0bcd\u0baa\u0bcb\u0b95\u0bcd \u0ba4\u0bc0\u0bb5\u0bc1\u0b95\u0bb3\u0bcd", 
  "ng": "\u0ba8\u0bc8\u0b9c\u0bc0\u0bb0\u0bbf\u0baf\u0bbe", 
  "nz": "\u0ba8\u0bbf\u0baf\u0bc2\u0bb8\u0bbf\u0bb2\u0bbe\u0ba8\u0bcd\u0ba4\u0bc1", 
  "kp": "\u0bb5\u0b9f\u0b95\u0bcd\u0b95\u0bc1 \u0b95\u0bca\u0bb0\u0bbf\u0baf\u0bbe", 
  "es": "\u0bb8\u0bcd\u0baa\u0bc6\u0baf\u0bbf\u0ba9\u0bcd", 
  "np": "\u0ba8\u0bc7\u0baa\u0bbe\u0bb2\u0bcd", 
  "so": "\u0b9a\u0bcb\u0bae\u0bbe\u0bb2\u0bbf\u0baf\u0bbe", 
  "nr": "\u0ba8\u0baf\u0bc2\u0bb0\u0bc2", 
  "nu": "\u0ba8\u0bbf\u0baf\u0bc2", 
  "fr": "\u0baa\u0bbf\u0bb0\u0bbe\u0ba9\u0bcd\u0bb8\u0bcd", 
  "io": "\u0baa\u0bbf\u0bb0\u0bbf\u0b9f\u0bcd\u0b9f\u0bbf\u0bb7\u0bcd \u0b87\u0ba8\u0bcd\u0ba4\u0bbf\u0baf \u0baa\u0bc6\u0bb0\u0bc1\u0b99\u0bcd\u0b95\u0b9f\u0bb2\u0bcd \u0baa\u0bbf\u0bb0\u0ba4\u0bc7\u0b9a\u0bae\u0bcd", 
  "ru": "\u0bb0\u0bb7\u0bcd\u0baf\u0ba9\u0bcd \u0b85\u0bae\u0bc8\u0baa\u0bcd\u0baa\u0bc1", 
  "kz": "\u0b95\u0bb8\u0b95\u0bcd\u0bb8\u0bcd\u0ba4\u0bbe\u0ba9\u0bcd", 
  "fi": "\u0baa\u0bbf\u0ba9\u0bcd\u0bb2\u0bbe\u0ba8\u0bcd\u0ba4\u0bc1", 
  "fj": "\u0b83\u0baa\u0bbf\u0b9c\u0bbf", 
  "fk": "\u0baa\u0bbe\u0b95\u0bcd\u0bb2\u0bbe\u0ba8\u0bcd\u0ba4\u0bc1 \u0ba4\u0bc0\u0bb5\u0bc1\u0b95\u0bb3\u0bcd (\u0bae\u0bbe\u0bb2\u0bcd\u0bb5\u0bbf\u0ba9\u0bb8\u0bcd)", 
  "sa": "\u0b9a\u0bb5\u0bc2\u0ba4\u0bbf \u0b85\u0bb0\u0bc7\u0baa\u0bbf\u0baf\u0bbe", 
  "fo": "\u0b83\u0baa\u0bbe\u0bb0\u0bcb \u0ba4\u0bc0\u0bb5\u0bc1\u0b95\u0bb3\u0bcd", 
  "sz": "\u0b9a\u0bc1\u0bb5\u0bbe\u0bb8\u0bcd\u0bb2\u0bbe\u0ba8\u0bcd\u0ba4\u0bc1", 
  "sy": "\u0b9a\u0bc8\u0bb0\u0bbf\u0baf\u0bbe", 
  "kg": "\u0b95\u0bc8\u0bb0\u0bcd\u0b9c\u0bbf\u0bb8\u0bcd\u0ba4\u0bbe\u0ba9\u0bcd", 
  "ke": "\u0b95\u0bc6\u0ba9\u0bcd\u0baf\u0bbe", 
  "sr": "\u0b9a\u0bc1\u0bb0\u0bbf\u0ba8\u0bbe\u0bae\u0bc0", 
  "ki": "\u0b95\u0bbf\u0bb0\u0bbf\u0baa\u0bbe\u0ba4\u0bcd\u0ba4\u0bbf", 
  "kh": "\u0b95\u0bae\u0bcd\u0baa\u0bcb\u0b9f\u0bbf\u0baf\u0bbe", 
  "sv": "\u0b8e\u0bb2\u0bcd \u0b9a\u0bb2\u0bcd\u0bb5\u0bc7\u0b9f\u0bb0\u0bcd", 
  "km": "\u0b95\u0bcb\u0bae\u0bcb\u0bb0\u0bcb\u0bb8\u0bcd", 
  "st": "\u0b9a\u0bcb \u0b9f\u0bcb\u0bae\u0bcd \u0bae\u0bb1\u0bcd\u0bb1\u0bc1\u0bae\u0bcd \u0baa\u0bcd\u0bb0\u0bbf\u0ba9\u0bcd\u0b9a\u0bbf\u0baa\u0bbf", 
  "sk": "\u0bb8\u0bcd\u0bb2\u0bcb\u0bb5\u0bbe\u0b95\u0bbf\u0baf\u0bbe", 
  "sj": "\u0b9a\u0bb5\u0bb2\u0bcd\u0baa\u0bbe\u0bb0\u0bcd\u0b9f\u0bcd \u0bae\u0bb1\u0bcd\u0bb1\u0bc1\u0bae\u0bcd \u0b9c\u0ba9\u0bcd \u0bae\u0bbe\u0baf\u0ba9\u0bcd", 
  "si": "\u0bb8\u0bcd\u0bb2\u0bcb\u0bb5\u0bc7\u0ba9\u0bbf\u0baf\u0bbe", 
  "sh": "\u0b9a\u0bc6\u0baf\u0bbf\u0ba9\u0bcd\u0b9f\u0bcd \u0bb9\u0bc7\u0bb2\u0bc0\u0ba9\u0bbe", 
  "kw": "\u0b95\u0bc1\u0bb5\u0bc8\u0ba4\u0bcd", 
  "sn": "\u0bb8\u0bcd\u0ba8\u0bc7\u0b95\u0bb2\u0bcd", 
  "sm": "\u0b9a\u0bc6\u0ba9\u0bcd \u0bae\u0bb0\u0bbf\u0ba8\u0bcb", 
  "sl": "\u0b9a\u0bbf\u0baf\u0bbe\u0bb0\u0bbe \u0bb2\u0bbf\u0baf\u0bcb\u0ba9\u0bcd", 
  "sc": "\u0b9a\u0bc8\u0b9a\u0bbf\u0bb2\u0bb8\u0bcd", 
  "sb": "\u0b9a\u0bbe\u0bb2\u0bae\u0bcb\u0ba9\u0bcd \u0ba4\u0bc0\u0bb5\u0bc1\u0b95\u0bb3\u0bcd", 
  "ky": "\u0b95\u0bc7\u0bae\u0bc7\u0ba9\u0bcd \u0ba4\u0bc0\u0bb5\u0bc1\u0b95\u0bb3\u0bcd", 
  "sg": "\u0b9a\u0bbf\u0b99\u0bcd\u0b95\u0baa\u0bcd\u0baa\u0bc2\u0bb0\u0bcd", 
  "se": "\u0b9a\u0bc1\u0bb5\u0bc0\u0b9f\u0ba9\u0bcd", 
  "sd": "\u0b9a\u0bc2\u0b9f\u0bbe\u0ba9\u0bcd"
}